embedhq/__init__.py
embedhq/_base_client.py
embedhq/_client.py
embedhq/_compat.py
embedhq/_constants.py
embedhq/_exceptions.py
embedhq/_files.py
embedhq/_models.py
embedhq/_qs.py
embedhq/_resource.py
embedhq/_response.py
embedhq/_streaming.py
embedhq/_types.py
embedhq/_version.py
embedhq/py.typed
embedhq/_utils/__init__.py
embedhq/_utils/_logs.py
embedhq/_utils/_proxy.py
embedhq/_utils/_reflection.py
embedhq/_utils/_streams.py
embedhq/_utils/_sync.py
embedhq/_utils/_transform.py
embedhq/_utils/_typing.py
embedhq/_utils/_utils.py
embedhq/lib/.keep
embedhq/resources/__init__.py
embedhq/resources/collections.py
embedhq/resources/connected_accounts.py
embedhq/resources/integrations.py
embedhq/resources/proxy.py
embedhq/resources/query.py
embedhq/resources/session_tokens.py
embedhq/resources/actions/__init__.py
embedhq/resources/actions/actions.py
embedhq/resources/actions/runs.py
embedhq/resources/providers/__init__.py
embedhq/resources/providers/action_templates.py
embedhq/resources/providers/collection_templates.py
embedhq/resources/providers/providers.py
embedhq/resources/syncs/__init__.py
embedhq/resources/syncs/runs.py
embedhq/resources/syncs/syncs.py
embedhq/resources/webhooks/__init__.py
embedhq/resources/webhooks/events.py
embedhq/resources/webhooks/webhooks.py
embedhq/types/__init__.py
embedhq/types/action.py
embedhq/types/action_create_params.py
embedhq/types/action_delete_params.py
embedhq/types/action_delete_response.py
embedhq/types/action_list_params.py
embedhq/types/action_list_response.py
embedhq/types/action_retrieve_params.py
embedhq/types/action_trigger_params.py
embedhq/types/action_trigger_response.py
embedhq/types/action_update_params.py
embedhq/types/collection.py
embedhq/types/collection_create_params.py
embedhq/types/collection_delete_params.py
embedhq/types/collection_delete_response.py
embedhq/types/collection_list_params.py
embedhq/types/collection_list_response.py
embedhq/types/collection_retrieve_params.py
embedhq-1.2.0.dist-info/METADATA
embedhq-1.2.0.dist-info/WHEEL
embedhq-1.2.0.dist-info/licenses/LICENSE
embedhq-1.2.0.dist-info/RECORD
